dj_configurator/__init__.py
dj_configurator/__main__.py
dj_configurator/asgi.py
dj_configurator/base.py
dj_configurator/decorators.py
dj_configurator/fastcgi.py
dj_configurator/importer.py
dj_configurator/management.py
dj_configurator/sphinx.py
dj_configurator/utils.py
dj_configurator/values.py
dj_configurator/version.py
dj_configurator/wsgi.py
django_configurator-1.3.1.dist-info/METADATA
django_configurator-1.3.1.dist-info/WHEEL
django_configurator-1.3.1.dist-info/entry_points.txt
django_configurator-1.3.1.dist-info/licenses/LICENSE
django_configurator-1.3.1.dist-info/RECORD
