Metadata-Version: 2.1
Name: django-configurator
Version: 1.3.1
Summary: Supports using class based settings for  Django and supports various setting object types with validation. This is a port of the original django-configurations project.
Author-Email: Christopher Broderick <chris@uhurutechnology.com>
License: BSD
Classifier: Development Status :: 5 - Production/Stable
Classifier: Framework :: Django
Classifier: Framework :: Django :: 4.1
Classifier: Framework :: Django :: 4.2
Classifier: Framework :: Django :: 5.0
Classifier: Framework :: Django :: 5.1
Classifier: Framework :: Django :: 5.2
Classifier: Intended Audience :: Developers
Classifier: License :: OSI Approved :: BSD License
Classifier: Operating System :: OS Independent
Classifier: Programming Language :: Python
Classifier: Programming Language :: Python :: 3
Classifier: Programming Language :: Python :: 3 :: Only
Classifier: Programming Language :: Python :: 3.9
Classifier: Programming Language :: Python :: 3.10
Classifier: Programming Language :: Python :: 3.11
Classifier: Programming Language :: Python :: 3.12
Classifier: Programming Language :: Python :: 3.13
Classifier: Programming Language :: Python :: Implementation :: PyPy
Classifier: Topic :: Utilities
Project-URL: Homepage, https://django-configurator.readthedocs.io/
Project-URL: Source, https://github.com/UhuruTechnology/django-configurator
Requires-Python: <4.0,>=3.9
Requires-Dist: django>=4.1
Provides-Extra: cache
Requires-Dist: django-cache-url; extra == "cache"
Provides-Extra: database
Requires-Dist: dj-database-url; extra == "database"
Provides-Extra: email
Requires-Dist: dj-email-url; extra == "email"
Provides-Extra: search
Requires-Dist: dj-search-url; extra == "search"
Provides-Extra: testing
Requires-Dist: dj-database-url; extra == "testing"
Requires-Dist: dj-email-url; extra == "testing"
Requires-Dist: dj-search-url; extra == "testing"
Requires-Dist: django-cache-url>=1.0.0; extra == "testing"
